fs/archive/__init__.py
fs/archive/_utils.py
fs/archive/_version.txt
fs/archive/base.py
fs/archive/opener.py
fs/archive/test.py
fs/archive/wrap.py
fs/archive/isofs/__init__.py
fs/archive/isofs/_utils.py
fs/archive/sevenzipfs/__init__.py
fs/archive/tarfs/__init__.py
fs/archive/tarfs/iotools.py
fs/archive/tarfs/tarfile2.py
fs/archive/zipfs/__init__.py
fs.archive-0.7.3.dist-info/COPYING
fs.archive-0.7.3.dist-info/METADATA
fs.archive-0.7.3.dist-info/WHEEL
fs.archive-0.7.3.dist-info/entry_points.txt
fs.archive-0.7.3.dist-info/top_level.txt
fs.archive-0.7.3.dist-info/zip-safe
fs.archive-0.7.3.dist-info/RECORD
