Metadata-Version: 2.1
Name: fs.archive
Version: 0.7.3
Summary: Enhanced archive filesystems for Pyfilesystem2
Home-page: https://github.com/althonos/fs.archive
Author: Martin Larralde
Author-email: martin.larralde@embl.de
License: MIT
Project-URL: Bug Tracker, https://github.com/althonos/fs.archive/issues
Project-URL: Changelog, https://github.com/althonos/fs.archive/blob/master/CHANGELOG.md
Project-URL: Coverage, https://codecov.io/gh/althonos/fs.archive
Project-URL: Builds, https://github.com/althonos/fs.archive/actions
Keywords: archive,zip,tar,iso,filesystem,Pyfilesystem2
Platform: any
Classifier: Development Status :: 4 - Beta
Classifier: Intended Audience :: Developers
Classifier: License :: OSI Approved :: MIT License
Classifier: Operating System :: OS Independent
Classifier: Programming Language :: Python
Classifier: Programming Language :: Python :: 2.7
Classifier: Programming Language :: Python :: 3.3
Classifier: Programming Language :: Python :: 3.4
Classifier: Programming Language :: Python :: 3.5
Classifier: Programming Language :: Python :: 3.6
Classifier: Programming Language :: Python :: 3.7
Classifier: Programming Language :: Python :: 3.8
Classifier: Programming Language :: Python :: 3.9
Classifier: Programming Language :: Python :: 3.10
Classifier: Topic :: Software Development :: Libraries :: Python Modules
Classifier: Topic :: System :: Filesystems
Requires-Python: !=3.0.*,!=3.1.*,!=3.2.*,>=2.7
License-File: COPYING
Requires-Dist: fs (~=2.2)
Requires-Dist: six (~=1.10)
Requires-Dist: setuptools (>=38.3.0)
Provides-Extra: 7z
Requires-Dist: py7zr (>=0.17.3) ; extra == '7z'
Requires-Dist: iocursor (~=0.1) ; extra == '7z'
Requires-Dist: typing (~=3.6) ; python_version < "3.6"
Provides-Extra: all
Requires-Dist: pycdlib (~=1.8) ; extra == 'all'
Requires-Dist: py7zr (>=0.17.3) ; extra == 'all'
Requires-Dist: iocursor (~=0.1) ; extra == 'all'
Requires-Dist: backports.lzma ; (python_version < "3") and extra == 'all'
Provides-Extra: iso
Requires-Dist: pycdlib (~=1.8) ; extra == 'iso'
Provides-Extra: tar.xz
Requires-Dist: backports.lzma ; (python_version < "3") and extra == 'tar.xz'
